{
	"cards": [
		{
			"id": 531,
			"name": "(Mysterious Charm) Himari Uehara",
			"nick": "himari",
			"alias": "sr1",
			"star": "3",
			"skname": "It's a Gift!",
			"skill": "Boosts score by +60% for 5, up to 7 seconds.",
			"stat": "Pure",
			"pf": 11174,
			"tech": 8452,
			"vis": 6823,
			"total": 26449,
			"origin": "Gacha: Initial Card",
			"icon": "http://i.bandori.party/u/c/531Himari-Uehara-Pure-t4eMj2.png",
			"img": "http://i.bandori.party/u/c/art/531Himari-Uehara-Pure-eeixHa.png",
			"imgbloomed": "http://i.bandori.party/u/c/art/a/531Himari-Uehara-Pure-WdG9jQ.png"
		},
		{
			"id": 667,
			"name": "(3 People Playing in the Water) Himari Uehara",
			"nick": "himari",
			"alias": "sr2",
			"star": "3",
			"skname": "I'm Definitely in the Ocean!",
			"skill": "Boosts score by +30% and turns GREAT+ notes into PERFECT notes for 5, up to 7.5 seconds.",
			"stat": "Cool",
			"pf": 10333,
			"tech": 7809,
			"vis": 9018,
			"total": 27160,
			"origin": "Limited Gacha: Summer Sky Ocean Blue (31 July 2017)",
			"icon": "http://i.bandori.party/u/c/667Himari-Uehara-Cool-XJtCRZ.png",
			"img": "http://i.bandori.party/u/c/art/667Himari-Uehara-Cool-z0uH3n.png",
			"imgbloomed": "http://i.bandori.party/u/c/art/a/667Himari-Uehara-Cool-m6GInk.png"
		}
	]
}