{
	"cards": [
		{
			"id": 563,
			"name": "(Surefire Idol Pose☆) Aya Maruyama",
			"nick": "aya",
			"alias": "sr1",
			"star": "3",
			"skname": "Aya'll Paint it!",
			"skill": "Turns Good+ notes into Perfect notes, and boosts score by +20% for 5, up to 8 seconds.",
			"stat": "Pure",
			"pf": 9827,
			"tech": 9297,
			"vis": 8239,
			"total": 27363,
			"origin": "Gacha: Initial Card",
			"icon": "http://i.bandori.party/u/c/563Aya-Maruyama-Pure-zgm21Y.png",
			"img": "http://i.bandori.party/u/c/art/563Aya-Maruyama-Pure-MBGuks.png",
			"imgbloomed": "http://i.bandori.party/u/c/art/a/563Aya-Maruyama-Pure-wKdlTH.png"
		},
		{
			"id": 653,
			"name": "(Working on Tanabata) Aya Maruyama",
			"nick": "aya",
			"alias": "sr2",
			"star": "3",
			"skname": "How are the Fries?",
			"skill": "Restores life by 300, up to 450, and boosts score by +20% for 5, up to 8 seconds.",
			"stat": "Powerful",
			"pf": 9549,
			"tech": 9325,
			"vis": 8713,
			"total": 27587,
			"origin": "Event: The Tanzaku that Wishes on the Stars (30 June 2017)",
			"icon": "http://i.bandori.party/u/c/653Aya-Maruyama-Power-yBCnJ5.png",
			"img": "http://i.bandori.party/u/c/art/653Aya-Maruyama-Power-rdqueA.png",
			"imgbloomed": "http://i.bandori.party/u/c/art/a/653Aya-Maruyama-Power-yQpZJH.png"
		},
		{
			"id": 763,
			"name": "(Go! Go!) Aya Maruyama",
			"nick": "aya",
			"alias": "sr3",
			"star": "3",
			"skname": "Specializing in Support",
			"skill": "Turns GOOD+ notes into PERFECT notes, and boosts score by +20% for 5, up to 8 seconds.",
			"stat": "Happy",
			"pf": 8917,
			"tech": 7421,
			"vis": 11199,
			"total": 27537,
			"origin": "Event: The Teary Smile Anchor (20 Oct 2017)",
			"icon": "http://i.bandori.party/u/c/763Aya-Maruyama-Happy-Puepuc.png",
			"img": "http://i.bandori.party/u/c/art/763Aya-Maruyama-Happy-VgIlJO.png",
			"imgbloomed": "http://i.bandori.party/u/c/art/a/763Aya-Maruyama-Happy-jzdM8j.png"
		},
		{
			"id": 887,
			"name": "(Maruyama, Arriving!) Aya Maruyama",
			"nick": "aya",
			"alias": "sr4",
			"star": "3",
			"skname": "Idol Maruyama Aya!",
			"skill": "Boosts score by +65% when life is above 900, or +55% if not for 5, up to 7 seconds.",
			"stat": "Cool",
			"pf": 9178,
			"tech": 10226,
			"vis": 8587,
			"total": 27991,
			"origin": "Gacha: Pastel*Bloom Girls (19 Feb 2018)",
			"icon": "https://i.bandori.party/u/c/887Aya-Maruyama-Cool-%E4%B8%B8%E5%B1%B1-%E5%85%A5%E3%82%8A%E3%81%BE%E3%81%99-YfqAxo.png",
			"img": "https://i.bandori.party/u/c/art/887Aya-Maruyama-Cool-%E4%B8%B8%E5%B1%B1-%E5%85%A5%E3%82%8A%E3%81%BE%E3%81%99-AttjIw.png",
			"imgbloomed": "https://i.bandori.party/u/c/art/a/887Aya-Maruyama-Cool-%E4%B8%B8%E5%B1%B1-%E5%85%A5%E3%82%8A%E3%81%BE%E3%81%99-V7JygN.png"
		},
		{
			"id": 901,
			"name": "(My Ideal Idol!) Aya Maruyama",
			"nick": "aya",
			"alias": "sr5",
			"star": "3",
			"skname": "It’s all for our fans from now on",
			"skill": "For the next 5 seconds, score of all notes boosted by +60.0%.",
			"stat": "Powerful",
			"pf": 6717,
			"tech": 11585,
			"vis": 8755,
			"total": 27057,
			"origin": "Event: Backstage Pass (10 March 2018)",
			"icon": "https://i.bandori.party/u/c/901Aya-Maruyama-Power-Aiming-to-be-a-Dream-Idol-uz7qKP.png",
			"img": "https://i.bandori.party/u/c/art/901Aya-Maruyama-Power-t46uMR.png",
			"imgbloomed": "https://i.bandori.party/u/c/art/a/901Aya-Maruyama-Power-WGCcaq.png"
		}
	]
}